MANIFEST.in
README.md
requirements.txt
setup.py
Pinhole.egg-info/PKG-INFO
Pinhole.egg-info/SOURCES.txt
Pinhole.egg-info/dependency_links.txt
Pinhole.egg-info/entry_points.txt
Pinhole.egg-info/requires.txt
Pinhole.egg-info/top_level.txt
pinhole/__init__.py
pinhole/run.py
pinhole/__pycache__/__init__.cpython-36.pyc