Metadata-Version: 1.0
Name: Pinhole
Version: 0.0.2
Summary: Less Is More.
Home-page: https://github.com/uid00000000/pinhole
Author: jayb
Author-email: markbrownjayb@qq.com
License: MIT
Platform: UNKNOWN
